yeaz/GUI_main.py
yeaz/Launch_NN_command_line.py
yeaz/__init__.py
yeaz/__main__.py
yeaz/_version.py
yeaz/disk/DialogFileBrowser.py
yeaz/disk/Reader.py
yeaz/disk/__init__.py
yeaz/disk/image_loader.py
yeaz/icons/HomeIcon.png
yeaz/icons/LeftArrowIcon.png
yeaz/icons/MoveArrowsIcon.png
yeaz/icons/RightArrowIcon.png
yeaz/icons/ZoomIcon.png
yeaz/icons/__init__.py
yeaz/icons/brush2.png
yeaz/icons/eraser.png
yeaz/init/InitButtons.py
yeaz/init/InitLayout.py
yeaz/init/__init__.py
yeaz/misc/BatchRetrack.py
yeaz/misc/ChangeOneCellValue.py
yeaz/misc/ExchangeCellValues.py
yeaz/misc/Extract.py
yeaz/misc/PlotCanvas.py
yeaz/misc/ProgressBar.py
yeaz/misc/__init__.py
yeaz/unet/LaunchBatchPrediction.py
yeaz/unet/__init__.py
yeaz/unet/hungarian.py
yeaz/unet/model_pytorch.py
yeaz/unet/model_tensorflow.py
yeaz/unet/neural_network.py
yeaz/unet/segment.py
yeaz/unet/utils.py
yeaz/unet/weights/__init__.py
YeaZ-1.0.3.dist-info/LICENSE
YeaZ-1.0.3.dist-info/METADATA
YeaZ-1.0.3.dist-info/WHEEL
YeaZ-1.0.3.dist-info/entry_points.txt
YeaZ-1.0.3.dist-info/top_level.txt
YeaZ-1.0.3.dist-info/RECORD
