Metadata-Version: 2.1
Name: YeaZ
Version: 1.0.3
Summary: Deep-learning based yeast cell segmentation
Home-page: https://github.com/rahi-lab/YeaZ-GUI
Author: Sahand Jamal Rahi
Author-email: sahand.rahi@epfl.ch
Project-URL: Rahi lab, https://www.epfl.ch/labs/lpbs/
Keywords: live-cell imaging,cell segmentation,cell tracking,image analysis
Classifier: Development Status :: 4 - Beta
Classifier: Programming Language :: Python :: 3 :: Only
Classifier: Programming Language :: Python :: 3.8
Classifier: Programming Language :: Python :: 3.9
Classifier: Programming Language :: Python :: 3.10
Classifier: License :: OSI Approved :: BSD License
Classifier: Intended Audience :: Education
Classifier: Intended Audience :: Science/Research
Classifier: Operating System :: Microsoft :: Windows
Classifier: Operating System :: POSIX
Classifier: Operating System :: Unix
Classifier: Operating System :: MacOS
Classifier: Topic :: Scientific/Engineering
Classifier: Topic :: Scientific/Engineering :: Bio-Informatics
Classifier: Topic :: Scientific/Engineering :: Information Analysis
Classifier: Topic :: Scientific/Engineering :: Image Processing
Classifier: Topic :: Scientific/Engineering :: Visualization
Classifier: Topic :: Utilities
Requires-Python: >=3.9
License-File: LICENSE
Requires-Dist: numpy >=1.17.4
Requires-Dist: matplotlib >=3.1.1
Requires-Dist: nd2reader >=3.3.0
Requires-Dist: h5py >=3.8.0
Requires-Dist: scikit-image >=0.15.0
Requires-Dist: openpyxl >=3.1.2
Requires-Dist: opencv-python-headless >=4.7.0.72
Requires-Dist: pandas >=0.25.3
Requires-Dist: munkres
Requires-Dist: scikit-learn >=0.0
Requires-Dist: imageio >=2.6.1
Requires-Dist: Pillow >=6.2.1
Requires-Dist: tqdm
Provides-Extra: gui
Requires-Dist: PyQt6 ; extra == 'gui'
Provides-Extra: tensorflow
Requires-Dist: tensorflow >=2.11.0 ; extra == 'tensorflow'
Provides-Extra: torch
Requires-Dist: torch >=2.0.0 ; extra == 'torch'
